{"minecraft:furnace":{"id":0,"valid_blocks":[153],"class":"FurnaceBlockEntity"},"minecraft:chest":{"id":1,"valid_blocks":[146],"class":"ChestBlockEntity"},"minecraft:trapped_chest":{"id":2,"valid_blocks":[326],"class":"TrappedChestBlockEntity"},"minecraft:ender_chest":{"id":3,"valid_blocks":[267],"class":"EnderChestBlockEntity"},"minecraft:jukebox":{"id":4,"valid_blocks":[189],"class":"JukeboxBlockEntity"},"minecraft:dispenser":{"id":5,"valid_blocks":[69],"class":"DispenserBlockEntity"},"minecraft:dropper":{"id":6,"valid_blocks":[339],"class":"DropperBlockEntity"},"minecraft:sign":{"id":7,"valid_blocks":[154,155,156,157,158,159,164,165,166,167,168,169,716,718,717,719],"class":"SignBlockEntity"},"minecraft:mob_spawner":{"id":8,"valid_blocks":[144],"class":"SpawnerBlockEntity"},"minecraft:piston":{"id":9,"valid_blocks":[117],"class":"PistonMovingBlockEntity"},"minecraft:brewing_stand":{"id":10,"valid_blocks":[257],"class":"BrewingStandBlockEntity"},"minecraft:enchanting_table":{"id":11,"valid_blocks":[256],"class":"EnchantmentTableBlockEntity"},"minecraft:end_portal":{"id":12,"valid_blocks":[259],"class":"TheEndPortalBlockEntity"},"minecraft:beacon":{"id":13,"valid_blocks":[275],"class":"BeaconBlockEntity"},"minecraft:skull":{"id":14,"valid_blocks":[311,312,319,320,321,322,315,316,313,314,317,318],"class":"SkullBlockEntity"},"minecraft:daylight_detector":{"id":15,"valid_blocks":[330],"class":"DaylightDetectorBlockEntity"},"minecraft:hopper":{"id":16,"valid_blocks":[333],"class":"HopperBlockEntity"},"minecraft:comparator":{"id":17,"valid_blocks":[329],"class":"ComparatorBlockEntity"},"minecraft:banner":{"id":18,"valid_blocks":[413,414,415,416,417,418,419,420,421,422,423,424,425,426,427,428,429,430,431,432,433,434,435,436,437,438,439,440,441,442,443,444],"class":"BannerBlockEntity"},"minecraft:structure_block":{"id":19,"valid_blocks":[720],"class":"StructureBlockEntity"},"minecraft:end_gateway":{"id":20,"valid_blocks":[496],"class":"TheEndGatewayBlockEntity"},"minecraft:command_block":{"id":21,"valid_blocks":[274,498,497],"class":"CommandBlockEntity"},"minecraft:shulker_box":{"id":22,"valid_blocks":[506,522,518,519,516,514,520,510,515,512,509,508,513,517,521,507,511],"class":"ShulkerBoxBlockEntity"},"minecraft:bed":{"id":23,"valid_blocks":[88,89,85,86,83,81,87,77,82,79,76,75,80,84,74,78],"class":"BedBlockEntity"},"minecraft:conduit":{"id":24,"valid_blocks":[617],"class":"ConduitBlockEntity"},"minecraft:barrel":{"id":25,"valid_blocks":[665],"class":"BarrelBlockEntity"},"minecraft:smoker":{"id":26,"valid_blocks":[666],"class":"SmokerBlockEntity"},"minecraft:blast_furnace":{"id":27,"valid_blocks":[667],"class":"BlastFurnaceBlockEntity"},"minecraft:lectern":{"id":28,"valid_blocks":[671],"class":"LecternBlockEntity"},"minecraft:bell":{"id":29,"valid_blocks":[674],"class":"BellBlockEntity"},"minecraft:jigsaw":{"id":30,"valid_blocks":[721],"class":"JigsawBlockEntity"},"minecraft:campfire":{"id":31,"valid_blocks":[677],"class":"CampfireBlockEntity"},"minecraft:beehive":{"id":32,"valid_blocks":[724,725],"class":"BeehiveBlockEntity"}}